voxel_select_client/__init__.py
voxel_select_client-0.1.0.dist-info/METADATA
voxel_select_client-0.1.0.dist-info/WHEEL
voxel_select_client-0.1.0.dist-info/top_level.txt
voxel_select_client-0.1.0.dist-info/RECORD
