Metadata-Version: 2.1
Name: voxel-select-client
Version: 0.1.0
Summary: Add your description here
Requires-Python: >=3.7
Requires-Dist: requests
